LICENSE
MANIFEST.in
README.md
requirements.txt
setup.cfg
setup.py
intelligentML/__init__.py
intelligentML/intelligentML.py
intelligentML.egg-info/PKG-INFO
intelligentML.egg-info/SOURCES.txt
intelligentML.egg-info/dependency_links.txt
intelligentML.egg-info/not-zip-safe
intelligentML.egg-info/requires.txt
intelligentML.egg-info/top_level.txt