Metadata-Version: 2.1
Name: intelligentML
Version: 0.1.1
Summary: An igent machine learning package. A Python library for handling duplicate data and performing data preprocessing on datasets. This library provides functions to identify and remove duplicate rows, handle missing values, and prepare data for analysis. All you have to do just provide the dataset url or path the library automatically do those tasks.
Home-page: https://github.com/Nasif-Azam/intelligentML
Author: Nasif Azam
Author-email: nasifazam07@gmail.com
License: MIT license
Keywords: intelligentML
Classifier: Intended Audience :: Developers
Classifier: License :: OSI Approved :: MIT License
Classifier: Natural Language :: English
Classifier: Programming Language :: Python :: 3
Classifier: Programming Language :: Python :: 3.8
Classifier: Programming Language :: Python :: 3.9
Classifier: Programming Language :: Python :: 3.10
Classifier: Programming Language :: Python :: 3.11
Requires-Python: >=3.8
License-File: LICENSE
